setup.py
cowboycushion/__init__.py
cowboycushion/limiter.py
cowboycushion/multiprocessing_limiter.py
cowboycushion.egg-info/PKG-INFO
cowboycushion.egg-info/SOURCES.txt
cowboycushion.egg-info/dependency_links.txt
cowboycushion.egg-info/requires.txt
cowboycushion.egg-info/top_level.txt
cowboycushion/tests/__init__.py
cowboycushion/tests/constants.py
cowboycushion/tests/test_limiter.py
cowboycushion/tests/test_multiprocessing_limiter.py