Metadata-Version: 1.0
Name: cowboycushion
Version: 0.3
Summary: Rate limiting libraries for Python API clients
Home-page: UNKNOWN
Author: Gregory Rehm
Author-email: UNKNOWN
License: UNKNOWN
Platform: UNKNOWN
